eulfedora/__init__.py
eulfedora/api.py
eulfedora/cryptutil.py
eulfedora/debug_panel.py
eulfedora/django_app.py
eulfedora/models.py
eulfedora/rdfns.py
eulfedora/server.py
eulfedora/syncutil.py
eulfedora/testutil.py
eulfedora/util.py
eulfedora/views.py
eulfedora/xml.py
eulfedora/indexdata/__init__.py
eulfedora/indexdata/models.py
eulfedora/indexdata/urls.py
eulfedora/indexdata/util.py
eulfedora/indexdata/views.py
eulfedora/management/__init__.py
eulfedora/management/commands/__init__.py
eulfedora/management/commands/syncrepo.py
eulfedora/templatetags/__init__.py
eulfedora/templatetags/fedora.py
eulfedora-1.7.2.data/scripts/fedora-checksums
eulfedora-1.7.2.data/scripts/repo-cp
eulfedora-1.7.2.data/scripts/validate-checksums
eulfedora-1.7.2.dist-info/DESCRIPTION.rst
eulfedora-1.7.2.dist-info/METADATA
eulfedora-1.7.2.dist-info/RECORD
eulfedora-1.7.2.dist-info/WHEEL
eulfedora-1.7.2.dist-info/metadata.json
eulfedora-1.7.2.dist-info/top_level.txt
scripts/__init__.py
scripts/download-test.py
scripts/fedora-checksums
scripts/repo-cp
scripts/upload-test.py
scripts/validate-checksums
test/__init__.py
test/localsettings.py
test/localsettings.py.dist
test/testsettings.py
test/test_fedora/__init__.py
test/test_fedora/base.py
test/test_fedora/test_api.py
test/test_fedora/test_cryptutil.py
test/test_fedora/test_models.py
test/test_fedora/test_server.py
test/test_fedora/test_syncutil.py
test/test_fedora/test_templatetags.py
test/test_fedora/test_util.py
test/test_fedora/test_views.py
test/test_indexdata/__init__.py
test/test_indexdata/test_util.py
test/test_indexdata/test_views.py
