Metadata-Version: 2.0
Name: eulfedora
Version: 1.7.2
Summary: Idiomatic access to digital objects in a Fedora Commons repository
Home-page: https://github.com/emory-libraries/eulfedora
Author: Emory University Libraries
Author-email: libsysdev-l@listserv.cc.emory.edu
License: Apache License, Version 2.0
Platform: UNKNOWN
Classifier: Development Status :: 5 - Production/Stable
Classifier: Framework :: Django
Classifier: Intended Audience :: Developers
Classifier: License :: OSI Approved :: Apache Software License
Classifier: Natural Language :: English
Classifier: Operating System :: OS Independent
Classifier: Programming Language :: Python
Classifier: Programming Language :: Python :: 2
Classifier: Programming Language :: Python :: 2.7
Classifier: Programming Language :: Python :: 3
Classifier: Programming Language :: Python :: 3.3
Classifier: Programming Language :: Python :: 3.4
Classifier: Programming Language :: Python :: 3.5
Classifier: Topic :: Software Development :: Libraries :: Python Modules
Requires-Dist: eulxml (>=1.0.1)
Requires-Dist: progressbar2
Requires-Dist: pycrypto
Requires-Dist: pypdf2
Requires-Dist: python-dateutil
Requires-Dist: rdflib (>=3.0)
Requires-Dist: requests (>2.9)
Requires-Dist: requests-toolbelt (>=0.6.0)
Requires-Dist: six
Provides-Extra: dev
Requires-Dist: Django; extra == 'dev'
Requires-Dist: coverage; extra == 'dev'
Requires-Dist: mock; extra == 'dev'
Requires-Dist: nose; extra == 'dev'
Requires-Dist: progressbar2; extra == 'dev'
Requires-Dist: pyPdf; extra == 'dev'
Requires-Dist: sphinx; extra == 'dev'
Requires-Dist: tox; extra == 'dev'
Provides-Extra: django
Requires-Dist: Django; extra == 'django'
Provides-Extra: indexdata_util
Requires-Dist: pypdf2; extra == 'indexdata_util'
Provides-Extra: test
Requires-Dist: coverage; extra == 'test'
Requires-Dist: mock; extra == 'test'
Requires-Dist: nose; extra == 'test'
Requires-Dist: progressbar2; extra == 'test'
Requires-Dist: pyPdf; extra == 'test'
Requires-Dist: sphinx; extra == 'test'
Requires-Dist: tox; extra == 'test'
